synthopt/__init__.py
synthopt/evaluate/__init__.py
synthopt/evaluate/privacy.py
synthopt/evaluate/quality.py
synthopt/evaluate/quality2.py
synthopt/evaluate/report.py
synthopt/evaluate/utility.py
synthopt/evaluate/visualisation.py
synthopt/generate/__init__.py
synthopt/generate/correlated_synthetic_data.py
synthopt/generate/data_generation.py
synthopt/generate/machine_learning.py
synthopt/generate/metadata.py
synthopt/generate/statistical.py
synthopt/generate/statistical_synthetic_data.py
synthopt/generate/structural_synthetic_data.py
synthopt/generate/syntheticdata.py
synthopt/optimise/__init__.py
synthopt/optimise/optimise.py
synthopt/process/__init__.py
synthopt/process/data_processing.py
synthopt/process/dpuk_processing.py
synthopt/process/metadata.py
synthopt/process/statistical_metadata.py
synthopt/process/structural_metadata.py
SynthOpt-0.2.26.dist-info/METADATA
SynthOpt-0.2.26.dist-info/WHEEL
SynthOpt-0.2.26.dist-info/top_level.txt
SynthOpt-0.2.26.dist-info/RECORD
