Metadata-Version: 2.1
Name: SynthOpt
Version: 0.2.26
Summary: A package for synthetic data generation, evaluation and optimisation.
Home-page: https://github.com/LewisHotchkissDPUK/SynthOpt
Author: Lewis Hotchkiss
Author-email: lewishotchkiss123@gmail.com
License: Apache License 2.0
Project-URL: Source Code, https://github.com/LewisHotchkissDPUK/SynthOpt
Requires-Dist: sdmetrics
Requires-Dist: sdv
Requires-Dist: synthcity
Requires-Dist: anonymeter
Requires-Dist: seaborn
Requires-Dist: reportlab
Requires-Dist: distfit
Requires-Dist: tqdm
